{
  "project_info": {
    "project_number": "535095694097",
    "project_id": "ecpmanager",
    "storage_bucket": "ecpmanager.firebasestorage.app"
  },
  "client": [
    {
      "client_info": {
        "mobilesdk_app_id": "1:535095694097:android:d7abcbcbc556dcf60832b0",
        "android_client_info": {
          "package_name": "com.excellerchezpierre.app"
        }
      },
      "oauth_client": [],
      "api_key": [
        {
          "current_key": "AIzaSyAGcEWXruMWOHExsbu2qWqNKZvyNFwaSeM"
        }
      ],
      "services": {
        "appinvite_service": {
          "other_platform_oauth_client": []
        }
      }
    }
  ],
  "configuration_version": "1"
}